geovdata/__init__.py
geovdata/ipython/__init__.py
geovdata/kit/__init__.py
geovdata/sparql/__init__.py
geovdata/sparql/connect.py
geovdata/sparql/execution.py
geovdata/sparql/globals.py
geovdata/sparql/helpers.py
geovdata-0.1.6.dist-info/LICENSE
geovdata-0.1.6.dist-info/METADATA
geovdata-0.1.6.dist-info/WHEEL
geovdata-0.1.6.dist-info/top_level.txt
geovdata-0.1.6.dist-info/RECORD
