Metadata-Version: 2.1
Name: geovdata
Version: 0.1.6
Summary: Package with various python tools
Author: Gaétan Muck
Author-email: gaetan.muck@kleiolab.com
Keywords: python,toolkit,utilities,utils,tools,sparql
License-File: LICENSE
Requires-Dist: pandas
Requires-Dist: gmpykit
Requires-Dist: SPARQLWrapper
